secsie/__init__.py
secsie/exceptions.py
secsie/generator.py
secsie/modes.py
secsie/parser.py
secsie_conf-3.1.3.dist-info/LICENSE
secsie_conf-3.1.3.dist-info/METADATA
secsie_conf-3.1.3.dist-info/WHEEL
secsie_conf-3.1.3.dist-info/top_level.txt
secsie_conf-3.1.3.dist-info/RECORD
