Metadata-Version: 2.1
Name: secsie-conf
Version: 3.1.3
Summary: A small library for parsing configuration files
Home-page: https://github.com/noahbroyles/secsie-conf
Author: Noah Broyles
Author-email: noah@javamate.net
License: MIT
Platform: UNKNOWN
Classifier: License :: OSI Approved :: MIT License
Classifier: Programming Language :: Python :: 3.7
Classifier: Programming Language :: Python :: 3.8
Classifier: Programming Language :: Python :: 3.9
Classifier: Programming Language :: Python :: 3.10
Classifier: Programming Language :: Python :: 3.11
Classifier: Programming Language :: Python :: 3.12
License-File: LICENSE
